{
    "mal_id": 50817,
    "url": "https://myanimelist.net/manga/50817/Makai_no_Ossan",
    "images": {
        "jpg": {
            "image_url": "https://cdn.myanimelist.net/images/manga/1/89755.jpg",
            "small_image_url": "https://cdn.myanimelist.net/images/manga/1/89755t.jpg",
            "large_image_url": "https://cdn.myanimelist.net/images/manga/1/89755l.jpg"
        },
        "webp": {
            "image_url": "https://cdn.myanimelist.net/images/manga/1/89755.webp",
            "small_image_url": "https://cdn.myanimelist.net/images/manga/1/89755t.webp",
            "large_image_url": "https://cdn.myanimelist.net/images/manga/1/89755l.webp"
        }
    },
    "approved": true,
    "titles": [
        {
            "type": "Default",
            "title": "Makai no Ossan"
        },
        {
            "type": "Synonym",
            "title": "Old Man of the Underworld"
        },
        {
            "type": "Japanese",
            "title": "魔界のオッサン"
        }
    ],
    "title": "Makai no Ossan",
    "title_english": null,
    "title_japanese": "魔界のオッサン",
    "title_synonyms": [
        "Old Man of the Underworld"
    ],
    "type": "Manga",
    "chapters": 370,
    "volumes": null,
    "status": "Finished",
    "publishing": false,
    "published": {
        "from": "2012-06-14T00:00:00+00:00",
        "to": "2013-06-15T00:00:00+00:00",
        "prop": {
            "from": {
                "day": 14,
                "month": 6,
                "year": 2012
            },
            "to": {
                "day": 15,
                "month": 6,
                "year": 2013
            }
        },
        "string": "Jun 14, 2012 to Jun 15, 2013"
    },
    "score": 7.12,
    "scored": 7.12,
    "scored_by": 1051,
    "rank": 7266,
    "popularity": 6877,
    "members": 3080,
    "favorites": 28,
    "synopsis": "Makai no Ossan is a slice-of-life-in-hell kind of gag web manga about an underworld family consisting of a middle-school student, his dad, mom, younger sister, and older brother.\n\n(Source: Boon Scanlations)",
    "background": "",
    "authors": [
        {
            "mal_id": 16993,
            "type": "people",
            "name": "ONE",
            "url": "https://myanimelist.net/people/16993/ONE"
        }
    ],
    "serializations": [
        {
            "mal_id": 290,
            "type": "manga",
            "name": "Tonari no Young Jump",
            "url": "https://myanimelist.net/manga/magazine/290/Tonari_no_Young_Jump"
        }
    ],
    "genres": [
        {
            "mal_id": 4,
            "type": "manga",
            "name": "Comedy",
            "url": "https://myanimelist.net/manga/genre/4/Comedy"
        },
        {
            "mal_id": 36,
            "type": "manga",
            "name": "Slice of Life",
            "url": "https://myanimelist.net/manga/genre/36/Slice_of_Life"
        },
        {
            "mal_id": 37,
            "type": "manga",
            "name": "Supernatural",
            "url": "https://myanimelist.net/manga/genre/37/Supernatural"
        }
    ],
    "explicit_genres": [],
    "themes": [
        {
            "mal_id": 6,
            "type": "manga",
            "name": "Mythology",
            "url": "https://myanimelist.net/manga/genre/6/Mythology"
        }
    ],
    "demographics": [
        {
            "mal_id": 41,
            "type": "manga",
            "name": "Seinen",
            "url": "https://myanimelist.net/manga/genre/41/Seinen"
        }
    ],
    "relations": [],
    "external": [
        {
            "name": "Official Site",
            "url": "http://tonarinoyj.jp/manga/makai/"
        },
        {
            "name": "Wikipedia",
            "url": "https://ja.wikipedia.org/wiki/%E9%AD%94%E7%95%8C%E3%81%AE%E3%82%AA%E3%83%83%E3%82%B5%E3%83%B3"
        }
    ]
}