{
    "mal_id": 13167,
    "url": "https://myanimelist.net/manga/13167/Benkyou_no_Jikan",
    "images": {
        "jpg": {
            "image_url": "https://cdn.myanimelist.net/images/manga/1/65651.jpg",
            "small_image_url": "https://cdn.myanimelist.net/images/manga/1/65651t.jpg",
            "large_image_url": "https://cdn.myanimelist.net/images/manga/1/65651l.jpg"
        },
        "webp": {
            "image_url": "https://cdn.myanimelist.net/images/manga/1/65651.webp",
            "small_image_url": "https://cdn.myanimelist.net/images/manga/1/65651t.webp",
            "large_image_url": "https://cdn.myanimelist.net/images/manga/1/65651l.webp"
        }
    },
    "approved": true,
    "titles": [
        {
            "type": "Default",
            "title": "Benkyou no Jikan"
        },
        {
            "type": "Synonym",
            "title": "So"
        },
        {
            "type": "Synonym",
            "title": "Stand by Me"
        },
        {
            "type": "Synonym",
            "title": "Green Days"
        },
        {
            "type": "Japanese",
            "title": "勉強の時間"
        }
    ],
    "title": "Benkyou no Jikan",
    "title_english": null,
    "title_japanese": "勉強の時間",
    "title_synonyms": [
        "So",
        "Stand by Me",
        "Green Days"
    ],
    "type": "Manga",
    "chapters": 3,
    "volumes": 1,
    "status": "Finished",
    "publishing": false,
    "published": {
        "from": "2008-08-25T00:00:00+00:00",
        "to": null,
        "prop": {
            "from": {
                "day": 25,
                "month": 8,
                "year": 2008
            },
            "to": {
                "day": null,
                "month": null,
                "year": null
            }
        },
        "string": "Aug 25, 2008"
    },
    "score": 7.24,
    "scored": 7.24,
    "scored_by": 2370,
    "rank": 5600,
    "popularity": 5065,
    "members": 4329,
    "favorites": 4,
    "synopsis": "When Nao recieves a terrible grade on the latest test, there's only one person to turn to: Andou-kun, the silent boy with his long hair covering his eyes. He gets great grades, and is semi-willing to help Nao out. Turns out that under all that hair, there's a cute boy...!\n\nIncludes 3 short stories:\n- Benkyou no Jikan\n- So, Stand by Me\n- Green Days\n\n(Source: Nagareboshi Manga)",
    "background": "",
    "authors": [
        {
            "mal_id": 7893,
            "type": "people",
            "name": "Minami, Touko",
            "url": "https://myanimelist.net/people/7893/Touko_Minami"
        }
    ],
    "serializations": [
        {
            "mal_id": 53,
            "type": "manga",
            "name": "Bessatsu Margaret",
            "url": "https://myanimelist.net/manga/magazine/53/Bessatsu_Margaret"
        }
    ],
    "genres": [
        {
            "mal_id": 22,
            "type": "manga",
            "name": "Romance",
            "url": "https://myanimelist.net/manga/genre/22/Romance"
        }
    ],
    "explicit_genres": [],
    "themes": [],
    "demographics": [
        {
            "mal_id": 25,
            "type": "manga",
            "name": "Shoujo",
            "url": "https://myanimelist.net/manga/genre/25/Shoujo"
        }
    ],
    "relations": [],
    "external": []
}