{
    "mal_id": 10418,
    "url": "https://myanimelist.net/manga/10418/Kanojo_no_Honnou",
    "images": {
        "jpg": {
            "image_url": "https://cdn.myanimelist.net/images/manga/2/264340.jpg",
            "small_image_url": "https://cdn.myanimelist.net/images/manga/2/264340t.jpg",
            "large_image_url": "https://cdn.myanimelist.net/images/manga/2/264340l.jpg"
        },
        "webp": {
            "image_url": "https://cdn.myanimelist.net/images/manga/2/264340.webp",
            "small_image_url": "https://cdn.myanimelist.net/images/manga/2/264340t.webp",
            "large_image_url": "https://cdn.myanimelist.net/images/manga/2/264340l.webp"
        }
    },
    "approved": true,
    "titles": [
        {
            "type": "Default",
            "title": "Kanojo no Honnou"
        },
        {
            "type": "Synonym",
            "title": "Her Instinct"
        },
        {
            "type": "Japanese",
            "title": "彼女の本能"
        },
        {
            "type": "English",
            "title": "Her Instinct"
        }
    ],
    "title": "Kanojo no Honnou",
    "title_english": "Her Instinct",
    "title_japanese": "彼女の本能",
    "title_synonyms": [
        "Her Instinct"
    ],
    "type": "Manga",
    "chapters": 5,
    "volumes": 1,
    "status": "Finished",
    "publishing": false,
    "published": {
        "from": "2007-01-01T00:00:00+00:00",
        "to": null,
        "prop": {
            "from": {
                "day": 1,
                "month": 1,
                "year": 2007
            },
            "to": {
                "day": null,
                "month": null,
                "year": null
            }
        },
        "string": "2007"
    },
    "score": 6.52,
    "scored": 6.52,
    "scored_by": 1216,
    "rank": 16304,
    "popularity": 7988,
    "members": 2557,
    "favorites": 7,
    "synopsis": "Compilation of short stories:\n\n1. Kanojo no Honnou\nFollowing a break up, distraught Natsume bumps into Aiji-kun who is just on his way to deliver a love letter to a mystery girl and so in her rage and bitterness, Natsume lies to Aiji-kun, completely unprepared for his response.\n\n2. Todoketai\nMana's mother is about to get remarried but who is this? Why does he know her name? It's the first time her heart has ever beat like this!\n\n3. Mekakushi no Joousama \nYoriko is a bit of a coward and is always being bullied. When delinquent Maki stands up for her she falls for him in a moment, but he only says she's irritating and moves on. Wishing more than anything she could talk to him normally, how far will Yoriko go to draw his attention?\n\n4. Multi-Vitamin\nIchimiya Ai is known as \"The Devilish Girl\" who frequently changes boyfriends. When kouhai Natsu confesses to her suddenly she agrees to go out, only to find him very different from her previous boyfriends. So why hasn't she broken up with him?\n\n5. Lovex2 de Kishi\n\n(Source: MU)",
    "background": "",
    "authors": [
        {
            "mal_id": 4321,
            "type": "people",
            "name": "Sakurada, Hina",
            "url": "https://myanimelist.net/people/4321/Hina_Sakurada"
        }
    ],
    "serializations": [
        {
            "mal_id": 124,
            "type": "manga",
            "name": "Cheese!",
            "url": "https://myanimelist.net/manga/magazine/124/Cheese"
        }
    ],
    "genres": [
        {
            "mal_id": 22,
            "type": "manga",
            "name": "Romance",
            "url": "https://myanimelist.net/manga/genre/22/Romance"
        }
    ],
    "explicit_genres": [],
    "themes": [],
    "demographics": [
        {
            "mal_id": 25,
            "type": "manga",
            "name": "Shoujo",
            "url": "https://myanimelist.net/manga/genre/25/Shoujo"
        }
    ],
    "relations": [],
    "external": []
}