{
    "mal_id": 41805,
    "url": "https://myanimelist.net/manga/41805/Hwaja",
    "images": {
        "jpg": {
            "image_url": "https://cdn.myanimelist.net/images/manga/1/158656.jpg",
            "small_image_url": "https://cdn.myanimelist.net/images/manga/1/158656t.jpg",
            "large_image_url": "https://cdn.myanimelist.net/images/manga/1/158656l.jpg"
        },
        "webp": {
            "image_url": "https://cdn.myanimelist.net/images/manga/1/158656.webp",
            "small_image_url": "https://cdn.myanimelist.net/images/manga/1/158656t.webp",
            "large_image_url": "https://cdn.myanimelist.net/images/manga/1/158656l.webp"
        }
    },
    "approved": true,
    "titles": [
        {
            "type": "Default",
            "title": "Hwaja"
        },
        {
            "type": "Japanese",
            "title": "화자"
        }
    ],
    "title": "Hwaja",
    "title_english": null,
    "title_japanese": "화자",
    "title_synonyms": [],
    "type": "Manhwa",
    "chapters": 10,
    "volumes": 2,
    "status": "Finished",
    "publishing": false,
    "published": {
        "from": "2011-06-06T00:00:00+00:00",
        "to": "2012-02-20T00:00:00+00:00",
        "prop": {
            "from": {
                "day": 6,
                "month": 6,
                "year": 2011
            },
            "to": {
                "day": 20,
                "month": 2,
                "year": 2012
            }
        },
        "string": "Jun 6, 2011 to Feb 20, 2012"
    },
    "score": 7.4,
    "scored": 7.4,
    "scored_by": 1229,
    "rank": 3822,
    "popularity": 5834,
    "members": 3696,
    "favorites": 39,
    "synopsis": "In an old abandoned house at a small city, lives a girl alone. Men often go see her with presents. In this same town lives a boy who dreams of being a hero. When they meet, the wheels of fate gonna turn for both of them and for all those involved with Hwaja.",
    "background": "",
    "authors": [
        {
            "mal_id": 18685,
            "type": "people",
            "name": "Hong, Jac-Ga",
            "url": "https://myanimelist.net/people/18685/Jac-Ga_Hong"
        }
    ],
    "serializations": [
        {
            "mal_id": 845,
            "type": "manga",
            "name": "Daum Webtoon",
            "url": "https://myanimelist.net/manga/magazine/845/Daum_Webtoon"
        }
    ],
    "genres": [
        {
            "mal_id": 8,
            "type": "manga",
            "name": "Drama",
            "url": "https://myanimelist.net/manga/genre/8/Drama"
        },
        {
            "mal_id": 7,
            "type": "manga",
            "name": "Mystery",
            "url": "https://myanimelist.net/manga/genre/7/Mystery"
        },
        {
            "mal_id": 22,
            "type": "manga",
            "name": "Romance",
            "url": "https://myanimelist.net/manga/genre/22/Romance"
        },
        {
            "mal_id": 36,
            "type": "manga",
            "name": "Slice of Life",
            "url": "https://myanimelist.net/manga/genre/36/Slice_of_Life"
        }
    ],
    "explicit_genres": [],
    "themes": [
        {
            "mal_id": 40,
            "type": "manga",
            "name": "Psychological",
            "url": "https://myanimelist.net/manga/genre/40/Psychological"
        }
    ],
    "demographics": [],
    "relations": [],
    "external": [
        {
            "name": "Official Site",
            "url": "http://cartoon.media.daum.net/webtoon/view/hwaja"
        },
        {
            "name": "Namu.wiki",
            "url": "https://namu.wiki/w/%ED%99%94%EC%9E%90(%EC%9B%B9%ED%88%B0)"
        }
    ]
}