{
    "mal_id": 110179,
    "url": "https://myanimelist.net/manga/110179/Asahi-senpai_no_Okiniiri",
    "images": {
        "jpg": {
            "image_url": "https://cdn.myanimelist.net/images/manga/1/202317.jpg",
            "small_image_url": "https://cdn.myanimelist.net/images/manga/1/202317t.jpg",
            "large_image_url": "https://cdn.myanimelist.net/images/manga/1/202317l.jpg"
        },
        "webp": {
            "image_url": "https://cdn.myanimelist.net/images/manga/1/202317.webp",
            "small_image_url": "https://cdn.myanimelist.net/images/manga/1/202317t.webp",
            "large_image_url": "https://cdn.myanimelist.net/images/manga/1/202317l.webp"
        }
    },
    "approved": true,
    "titles": [
        {
            "type": "Default",
            "title": "Asahi-senpai no Okiniiri"
        },
        {
            "type": "Japanese",
            "title": "あさひ先輩のお気にいり"
        },
        {
            "type": "English",
            "title": "Asahi-sempai's Favorite"
        }
    ],
    "title": "Asahi-senpai no Okiniiri",
    "title_english": "Asahi-sempai's Favorite",
    "title_japanese": "あさひ先輩のお気にいり",
    "title_synonyms": [],
    "type": "Manga",
    "chapters": 28,
    "volumes": 7,
    "status": "Finished",
    "publishing": false,
    "published": {
        "from": "2017-06-13T00:00:00+00:00",
        "to": "2019-12-13T00:00:00+00:00",
        "prop": {
            "from": {
                "day": 13,
                "month": 6,
                "year": 2017
            },
            "to": {
                "day": 13,
                "month": 12,
                "year": 2019
            }
        },
        "string": "Jun 13, 2017 to Dec 13, 2019"
    },
    "score": 6.76,
    "scored": 6.76,
    "scored_by": 1112,
    "rank": 12802,
    "popularity": 6304,
    "members": 3391,
    "favorites": 11,
    "synopsis": "Poor first year high school student Matsuri has an awkward encounter with her older brother's extremely popular friend Asahi one day after she gets out of the bath! Ever since then, whether she's home, at school, or wherever, Asahi seems to meddle with her…! Her days have gotten a little sweeter, flirtier, and naughtier when she spends them around Asahi, and it's awful!\n\n(Source: Tokyo Otaku Mode)",
    "background": "Asahi-senpai no Okiniiri was published digitally in English as Asahi-sempai's Favorite by Kodansha Comics USA from March 26, 2019 to June 23, 2020.",
    "authors": [
        {
            "mal_id": 26145,
            "type": "people",
            "name": "Machino, Iroha",
            "url": "https://myanimelist.net/people/26145/Iroha_Machino"
        }
    ],
    "serializations": [
        {
            "mal_id": 111,
            "type": "manga",
            "name": "Bessatsu Friend",
            "url": "https://myanimelist.net/manga/magazine/111/Bessatsu_Friend"
        }
    ],
    "genres": [
        {
            "mal_id": 22,
            "type": "manga",
            "name": "Romance",
            "url": "https://myanimelist.net/manga/genre/22/Romance"
        }
    ],
    "explicit_genres": [],
    "themes": [
        {
            "mal_id": 23,
            "type": "manga",
            "name": "School",
            "url": "https://myanimelist.net/manga/genre/23/School"
        }
    ],
    "demographics": [
        {
            "mal_id": 25,
            "type": "manga",
            "name": "Shoujo",
            "url": "https://myanimelist.net/manga/genre/25/Shoujo"
        }
    ],
    "relations": [],
    "external": [
        {
            "name": "KodanshaKodansha USA",
            "url": "https://kodansha.us/series/asahi-sempais-favorite/"
        },
        {
            "name": "Official Site",
            "url": "https://betsufure.net/comics_end/1000030129.html"
        }
    ]
}