{
    "mal_id": 149135,
    "url": "https://myanimelist.net/manga/149135/Not-Sew-Wicked_Stepmom",
    "images": {
        "jpg": {
            "image_url": "https://cdn.myanimelist.net/images/manga/3/264637.jpg",
            "small_image_url": "https://cdn.myanimelist.net/images/manga/3/264637t.jpg",
            "large_image_url": "https://cdn.myanimelist.net/images/manga/3/264637l.jpg"
        },
        "webp": {
            "image_url": "https://cdn.myanimelist.net/images/manga/3/264637.webp",
            "small_image_url": "https://cdn.myanimelist.net/images/manga/3/264637t.webp",
            "large_image_url": "https://cdn.myanimelist.net/images/manga/3/264637l.webp"
        }
    },
    "approved": true,
    "titles": [
        {
            "type": "Default",
            "title": "Not-Sew-Wicked Stepmom"
        },
        {
            "type": "Synonym",
            "title": "I'm the Stepmother"
        },
        {
            "type": "Synonym",
            "title": "but My Daughter Is Too Cute"
        },
        {
            "type": "Synonym",
            "title": "I'm Only a Stepmother"
        },
        {
            "type": "Synonym",
            "title": "but My Daughter Is Just so Cute!"
        },
        {
            "type": "Synonym",
            "title": "Gyemo-inde Ttar-i Neomu Gwiyeowo"
        },
        {
            "type": "Japanese",
            "title": "계모인데 딸이 너무 귀여워"
        },
        {
            "type": "English",
            "title": "Not-Sew-Wicked Stepmom"
        }
    ],
    "title": "Not-Sew-Wicked Stepmom",
    "title_english": "Not-Sew-Wicked Stepmom",
    "title_japanese": "계모인데 딸이 너무 귀여워",
    "title_synonyms": [
        "I'm the Stepmother",
        "but My Daughter Is Too Cute",
        "I'm Only a Stepmother",
        "but My Daughter Is Just so Cute!",
        "Gyemo-inde Ttar-i Neomu Gwiyeowo"
    ],
    "type": "Manhwa",
    "chapters": null,
    "volumes": null,
    "status": "Publishing",
    "publishing": true,
    "published": {
        "from": "2021-04-10T00:00:00+00:00",
        "to": null,
        "prop": {
            "from": {
                "day": 10,
                "month": 4,
                "year": 2021
            },
            "to": {
                "day": null,
                "month": null,
                "year": null
            }
        },
        "string": "Apr 10, 2021 to ?"
    },
    "score": 7.51,
    "scored": 7.51,
    "scored_by": 1836,
    "rank": 2894,
    "popularity": 3490,
    "members": 6413,
    "favorites": 42,
    "synopsis": "Although Lee Lily's childhood dream to become a princess seems unattainable because of her average appearance, she finds her passion in designing children's clothes. Ultimately, her job results in her demise, as she works herself to death at the age of 30.\n\nLily is reincarnated in what appears to be the tale of Snow White as the story's villainess—the cruel and vain queen Abigail Freidkin. Now in Abigail's body, Lily wishes to befriend her stepdaughter Blanche, a sweet girl and her latest muse. However, it is a challenging feat, as Blanche fears her stepmother.\n\nFurthermore, Sabrian—the current king and Abigail's spouse—may be an outstanding regent, but as a father and husband, he is uncaring and neglectful. Although she is not fond of Sabrian, Abigail will go to any length to fix the broken relationship between the Freidkins and give her stepdaughter the happiest of endings.\n\n[Written by MAL Rewrite]",
    "background": "Not-Sew-Wicked Stepmom is originally a webtoon series which has been published in book format by A.Tempo Media (에이템포미디어) since July 6, 2022. The series has been published digitally in English by Tapas Media since October 28, 2021. The volumes have been published by Yen Press under the Ize Press imprint since August 22, 2023.",
    "authors": [
        {
            "mal_id": 59634,
            "type": "people",
            "name": "Ilu",
            "url": "https://myanimelist.net/people/59634/Ilu"
        },
        {
            "mal_id": 59635,
            "type": "people",
            "name": "Moguraeng",
            "url": "https://myanimelist.net/people/59635/Moguraeng"
        }
    ],
    "serializations": [
        {
            "mal_id": 1439,
            "type": "manga",
            "name": "KakaoPage",
            "url": "https://myanimelist.net/manga/magazine/1439/KakaoPage"
        }
    ],
    "genres": [
        {
            "mal_id": 10,
            "type": "manga",
            "name": "Fantasy",
            "url": "https://myanimelist.net/manga/genre/10/Fantasy"
        }
    ],
    "explicit_genres": [],
    "themes": [
        {
            "mal_id": 62,
            "type": "manga",
            "name": "Isekai",
            "url": "https://myanimelist.net/manga/genre/62/Isekai"
        },
        {
            "mal_id": 81,
            "type": "manga",
            "name": "Villainess",
            "url": "https://myanimelist.net/manga/genre/81/Villainess"
        }
    ],
    "demographics": [],
    "relations": [],
    "external": [
        {
            "name": "Official Site",
            "url": "https://page.kakao.com/home?seriesId=56714856"
        }
    ]
}