{
    "mal_id": 25679,
    "url": "https://myanimelist.net/manga/25679/Hentai_Ouji_to_Warawanai_Neko",
    "images": {
        "jpg": {
            "image_url": "https://cdn.myanimelist.net/images/manga/3/207423.jpg",
            "small_image_url": "https://cdn.myanimelist.net/images/manga/3/207423t.jpg",
            "large_image_url": "https://cdn.myanimelist.net/images/manga/3/207423l.jpg"
        },
        "webp": {
            "image_url": "https://cdn.myanimelist.net/images/manga/3/207423.webp",
            "small_image_url": "https://cdn.myanimelist.net/images/manga/3/207423t.webp",
            "large_image_url": "https://cdn.myanimelist.net/images/manga/3/207423l.webp"
        }
    },
    "approved": true,
    "titles": [
        {
            "type": "Default",
            "title": "Hentai Ouji to Warawanai Neko."
        },
        {
            "type": "Synonym",
            "title": "Perverted Prince and the Cat who doesn't Smile"
        },
        {
            "type": "Japanese",
            "title": "変態王子と笑わない猫。"
        },
        {
            "type": "English",
            "title": "The Hentai Prince and Stony Cat"
        }
    ],
    "title": "Hentai Ouji to Warawanai Neko.",
    "title_english": "The Hentai Prince and Stony Cat",
    "title_japanese": "変態王子と笑わない猫。",
    "title_synonyms": [
        "Perverted Prince and the Cat who doesn't Smile"
    ],
    "type": "Manga",
    "chapters": 52,
    "volumes": 8,
    "status": "Finished",
    "publishing": false,
    "published": {
        "from": "2011-04-27T00:00:00+00:00",
        "to": "2018-02-27T00:00:00+00:00",
        "prop": {
            "from": {
                "day": 27,
                "month": 4,
                "year": 2011
            },
            "to": {
                "day": 27,
                "month": 2,
                "year": 2018
            }
        },
        "string": "Apr 27, 2011 to Feb 27, 2018"
    },
    "score": 7.38,
    "scored": 7.38,
    "scored_by": 5014,
    "rank": 3989,
    "popularity": 1350,
    "members": 15514,
    "favorites": 114,
    "synopsis": "Yokodera is just like every teenage boy: perversion is in his nature. He can't help but look up girls' skirts and fantasize about them. However, in his case, every time he does something perverted, it somehow gets turned around and misunderstood as something positive for the community. Sick of being so perverted, he tries to shake free of it by going to a special part of town. On top of a hill, away from the town and at the foot of a large tree, there is a wooden sculpture of a beckoning cat that is said to have special powers. Instead of bringing a wish to the user like a typical beckoning cat, it takes something from the user, and, in Yokodera's case, his perversion. Still doubtful, he uses the beckoning cat thinking that it couldn't hurt to try, but, little does he know, his life is about to make a turn to the unexpected.\n\n(Source: MangaHelpers)",
    "background": "Hentai Ouji to Warawanai Neko. has been published digitally in English as The Hentai Prince and Stony Cat by Digital Manga Publishing since October 31, 2013. It has been published in Russian by XL Media since 2013.",
    "authors": [
        {
            "mal_id": 12462,
            "type": "people",
            "name": "Sagara, Sou",
            "url": "https://myanimelist.net/people/12462/Sou_Sagara"
        },
        {
            "mal_id": 12463,
            "type": "people",
            "name": "Okomeken",
            "url": "https://myanimelist.net/people/12463/Okomeken"
        }
    ],
    "serializations": [
        {
            "mal_id": 137,
            "type": "manga",
            "name": "Comic Alive",
            "url": "https://myanimelist.net/manga/magazine/137/Comic_Alive"
        }
    ],
    "genres": [
        {
            "mal_id": 4,
            "type": "manga",
            "name": "Comedy",
            "url": "https://myanimelist.net/manga/genre/4/Comedy"
        },
        {
            "mal_id": 22,
            "type": "manga",
            "name": "Romance",
            "url": "https://myanimelist.net/manga/genre/22/Romance"
        },
        {
            "mal_id": 9,
            "type": "manga",
            "name": "Ecchi",
            "url": "https://myanimelist.net/manga/genre/9/Ecchi"
        }
    ],
    "explicit_genres": [],
    "themes": [
        {
            "mal_id": 23,
            "type": "manga",
            "name": "School",
            "url": "https://myanimelist.net/manga/genre/23/School"
        }
    ],
    "demographics": [
        {
            "mal_id": 41,
            "type": "manga",
            "name": "Seinen",
            "url": "https://myanimelist.net/manga/genre/41/Seinen"
        }
    ],
    "relations": [
        {
            "relation": "Adaptation",
            "entry": [
                {
                    "mal_id": 25876,
                    "type": "manga",
                    "name": "Hentai Ouji to Warawanai Neko.",
                    "url": "https://myanimelist.net/manga/25876/Hentai_Ouji_to_Warawanai_Neko"
                },
                {
                    "mal_id": 15225,
                    "type": "anime",
                    "name": "Hentai Ouji to Warawanai Neko.",
                    "url": "https://myanimelist.net/anime/15225/Hentai_Ouji_to_Warawanai_Neko"
                }
            ]
        }
    ],
    "external": [
        {
            "name": "Wikipedia",
            "url": "https://ja.wikipedia.org/wiki/%E5%A4%89%E6%85%8B%E7%8E%8B%E5%AD%90%E3%81%A8%E7%AC%91%E3%82%8F%E3%81%AA%E3%81%84%E7%8C%AB%E3%80%82"
        }
    ]
}